rdpywheel/__init__.py
rdpywheel/sample.py
rdpywheel/auth/JtwHandler.py
rdpywheel/auth/__init__.py
rdpywheel/config/__init__.py
rdpywheel/config/config_reader.py
rdpywheel/model/__init__.py
rdpywheel/model/rest_response.py
rdpywheel/model/sms_platform.py
rdpywheel/sms/__init__.py
rdpywheel/sms/cn_virt_msg.py
rdpywheel/sms/sms_util.py
rdpywheel/sms/visa_test.py
rdpywheel/tool/__init__.py
rdpywheel/tool/sec/SecUtil.py
rdpywheel/tool/sec/__init__.py
rdpywheel/utils/__init__.py
rdpywheel/utils/rd_time_utils.py
tests/__init__.py
rdpywheel-0.1.22.dist-info/LICENSE
rdpywheel-0.1.22.dist-info/METADATA
rdpywheel-0.1.22.dist-info/WHEEL
rdpywheel-0.1.22.dist-info/top_level.txt
rdpywheel-0.1.22.dist-info/RECORD
