Metadata-Version: 2.1
Name: rdpywheel
Version: 0.1.22
Summary: reddwarf public python lib
Home-page: https://github.com/jiangxiaoqiang/rdpywheel
Author: jiangxiaoqiang
Author-email: jiang qiang <jiangtingqiang@gmail.com>
License: MIT
Keywords: wheel
Platform: any
Requires-Python: >=3.10
License-File: LICENSE
Requires-Dist: setuptools ~=68.1.2
Requires-Dist: requests ~=2.28.2
Requires-Dist: python-dotenv ==1.0.0
Requires-Dist: pycryptodome >=3.19.0
Requires-Dist: jwt >=1.3.1
Requires-Dist: twine >=4.0.2
